tror_yong_lm/__init__.py
tror_yong_lm/_version.py
tror_yong_lm/common.py
tror_yong_lm/generate.py
tror_yong_lm/nn_utils.py
tror_yong_lm/slm.py
tror_yong_lm-0.0.1.dist-info/licenses/LICENSE
tror_yong_lm-0.0.1.dist-info/METADATA
tror_yong_lm-0.0.1.dist-info/WHEEL
tror_yong_lm-0.0.1.dist-info/top_level.txt
tror_yong_lm-0.0.1.dist-info/RECORD
